{
  "neighborhoods": [
    {
      "name": "Atwood",
      "coords": [
        -89.3433421,
        43.0936497
      ],
      "price": 560550.0,
      "links": {
        "zillow": "https://www.zillow.com/schenk-atwood-madison-wi/?searchQueryState=%7B%22isMapVisible%22%3Atrue%2C%22mapBounds%22%3A%7B%22north%22%3A43.10456074592364%2C%22south%22%3A43.08168350614931%2C%22east%22%3A-89.33005228030395%2C%22west%22%3A-89.36176671969604%7D%2C%22filterState%22%3A%7B%22sort%22%3A%7B%22value%22%3A%22globalrelevanceex%22%7D%7D%2C%22isListVisible%22%3Atrue%2C%22mapZoom%22%3A15%2C%22usersSearchTerm%22%3A%22Schenk-Atwood%2C%20Madison%2C%20WI%22%2C%22regionSelection%22%3A%5B%7B%22regionId%22%3A272239%2C%22regionType%22%3A8%7D%5D%7D",
        "realtor": "https://www.realtor.com/realestateandhomes-search/Schenk-Atwood_Madison_WI",
        "redfin": "https://www.redfin.com/neighborhood/77391/WI/Madison/Schenk-Atwood",
        "homes": "https://www.homes.com/madison-wi/atwood-neighborhood/"
      },
      "data_links": {
        "zillow_data": "https://www.zillow.com/home-values/272239/schenk-atwood-madison-wi/",
        "realtor_data": "https://www.realtor.com/realestateandhomes-search/Schenk-Atwood_Madison_WI",
        "redfin_data": "https://www.redfin.com/neighborhood/77391/WI/Madison/Schenk-Atwood",
        "homes_data": "https://www.homes.com/madison-wi/atwood-neighborhood/"
      }
    },
    {
      "name": "Arbor Hills",
      "coords": [
        -89.43047729999999,
        43.0290077
      ],
      "price": 519390.0,
      "links": {
        "zillow": null,
        "realtor": null,
        "redfin": null,
        "homes": null
      },
      "data_links": {
        "zillow_data": null,
        "realtor_data": null,
        "redfin_data": null,
        "homes_data": null
      }
    }
  ]
}